turnstile_solver/__init__.py
turnstile_solver/clicker.py
turnstile_solver/detector.py
turnstile_solver/matcher.py
turnstile_solver/observer.py
turnstile_solver/solver.py
turnstile_solver/assets/dark_turnstile.png
turnstile_solver/assets/light_turnstile.png
turnstile_solver-0.1.4.dist-info/licenses/LICENSE
turnstile_solver-0.1.4.dist-info/METADATA
turnstile_solver-0.1.4.dist-info/WHEEL
turnstile_solver-0.1.4.dist-info/top_level.txt
turnstile_solver-0.1.4.dist-info/RECORD
