Metadata-Version: 2.4
Name: turnstile_solver
Version: 0.1.4
Summary: Click and solve Cloudflare Turnstile CAPTCHA — supports both headless and GUI modes.
Author-email: Hasnain Shahid <hasnainshahid822@gmail.com>
License: MIT
Project-URL: Homepage, https://github.com/hasnainshahidx/turnstile_solver/
Project-URL: Repository, https://github.com/hasnainshahidx/turnstile_solver/
Project-URL: Author, https://hasnainshahidx.github.io/
Keywords: captcha-solver,turnstile-solver,cloudflare-bypass,solver,automation
Classifier: License :: OSI Approved :: MIT License
Classifier: Programming Language :: Python :: 3
Classifier: Operating System :: OS Independent
Requires-Python: >=3.7
License-File: LICENSE
Requires-Dist: numpy
Requires-Dist: opencv-python
Requires-Dist: pyautogui
Requires-Dist: selenium
Dynamic: license-file
